caosadvancedtools/__init__.py
caosadvancedtools/cache.py
caosadvancedtools/cfood.py
caosadvancedtools/collect_datamodel.py
caosadvancedtools/crawler.py
caosadvancedtools/datainconsistency.py
caosadvancedtools/datamodel_problems.py
caosadvancedtools/example_cfood.py
caosadvancedtools/export_related.py
caosadvancedtools/guard.py
caosadvancedtools/import_from_xml.py
caosadvancedtools/json_schema_exporter.py
caosadvancedtools/loadFiles.py
caosadvancedtools/pandoc_header_tools.py
caosadvancedtools/read_md_header.py
caosadvancedtools/structure_mapping.py
caosadvancedtools/suppressKnown.py
caosadvancedtools/table_converter.py
caosadvancedtools/table_export.py
caosadvancedtools/table_importer.py
caosadvancedtools/utils.py
caosadvancedtools/version.py
caosadvancedtools/webui_formatter.py
caosadvancedtools/cfoods/__init__.py
caosadvancedtools/cfoods/h5.py
caosadvancedtools/models/__init__.py
caosadvancedtools/models/data_model.py
caosadvancedtools/models/parser.py
caosadvancedtools/scifolder/__init__.py
caosadvancedtools/scifolder/analysis_cfood.py
caosadvancedtools/scifolder/experiment_cfood.py
caosadvancedtools/scifolder/generic_pattern.py
caosadvancedtools/scifolder/publication_cfood.py
caosadvancedtools/scifolder/result_table_cfood.py
caosadvancedtools/scifolder/simulation_cfood.py
caosadvancedtools/scifolder/software_cfood.py
caosadvancedtools/scifolder/utils.py
caosadvancedtools/scifolder/withreadme.py
caosadvancedtools/serverside/__init__.py
caosadvancedtools/serverside/generic_analysis.py
caosadvancedtools/serverside/helper.py
caosadvancedtools/serverside/logging.py
caosadvancedtools/serverside/sync.py
caosadvancedtools/table_json_conversion/__init__.py
caosadvancedtools/table_json_conversion/_validation_utils.py
caosadvancedtools/table_json_conversion/convert.py
caosadvancedtools/table_json_conversion/export_import_xlsx.py
caosadvancedtools/table_json_conversion/fill_xlsx.py
caosadvancedtools/table_json_conversion/table_generator.py
caosadvancedtools-0.15.0.dist-info/LICENSE.md
caosadvancedtools-0.15.0.dist-info/METADATA
caosadvancedtools-0.15.0.dist-info/WHEEL
caosadvancedtools-0.15.0.dist-info/entry_points.txt
caosadvancedtools-0.15.0.dist-info/top_level.txt
caosadvancedtools-0.15.0.dist-info/RECORD
