Metadata-Version: 2.1
Name: caosadvancedtools
Version: 0.15.0
Summary: Advanced utilities for LinkAhead
Author: Henrik tom Wörden
Author-email: h.tomwoerden@indiscale.com
Requires-Python: >=3.9
License-File: LICENSE.md
Requires-Dist: linkahead >0.17.0
Requires-Dist: jsonref
Requires-Dist: jsonschema[format] >=4.4.0
Requires-Dist: numpy >=1.24.0
Requires-Dist: openpyxl !=3.1.3,>=3.1.2
Requires-Dist: pandas >=1.2.0
Requires-Dist: xlrd >=2.0
Provides-Extra: all
Requires-Dist: caosadvancedtools[dev,doc,test] ; extra == 'all'
Provides-Extra: dev
Requires-Dist: autopep8 ; extra == 'dev'
Requires-Dist: pycodestyle ; extra == 'dev'
Requires-Dist: pylint ; extra == 'dev'
Provides-Extra: doc
Requires-Dist: sphinx ; extra == 'doc'
Requires-Dist: sphinx-autoapi ; extra == 'doc'
Requires-Dist: sphinx-rtd-theme ; extra == 'doc'
Requires-Dist: recommonmark >=0.6.0 ; extra == 'doc'
Provides-Extra: gitignore-parser
Requires-Dist: gitignore-parser >=0.1.0 ; extra == 'gitignore-parser'
Provides-Extra: h5
Requires-Dist: h5py >=3.3.0 ; extra == 'h5'
Provides-Extra: test
Requires-Dist: pytest ; extra == 'test'
Requires-Dist: pytest-pythonpath ; extra == 'test'
Requires-Dist: pytest-cov ; extra == 'test'
Requires-Dist: coverage >=4.4.2 ; extra == 'test'
Requires-Dist: caosadvancedtools[gitignore-parser,h5] ; extra == 'test'
